wyld_api/__init__.py
wyld_api/client.py
wyld_api/py.typed
wyld_api/schemas.py
wyld_api-0.1.1.dist-info/METADATA
wyld_api-0.1.1.dist-info/WHEEL
wyld_api-0.1.1.dist-info/licenses/LICENSE
wyld_api-0.1.1.dist-info/RECORD
