Metadata-Version: 2.4
Name: wyld-api
Version: 0.1.1
Summary: A Python client for Wyld Network's Satellite IoT API with support for custom payload schemas
Project-URL: Homepage, https://github.com/Jobenas/wyld_api_client
Project-URL: Documentation, https://github.com/Jobenas/wyld_api_client#readme
Project-URL: Repository, https://github.com/Jobenas/wyld_api_client
Project-URL: Bug Tracker, https://github.com/Jobenas/wyld_api_client/issues
Author-email: Your Name <your.email@example.com>
Maintainer-email: Your Name <your.email@example.com>
License: MIT
License-File: LICENSE
Keywords: api-client,iot,network,pydantic,satellite,satellite-iot,wyld
Classifier: Development Status :: 3 - Alpha
Classifier: Intended Audience :: Developers
Classifier: License :: OSI Approved :: MIT License
Classifier: Operating System :: OS Independent
Classifier: Programming Language :: Python :: 3
Classifier: Programming Language :: Python :: 3.9
Classifier: Programming Language :: Python :: 3.10
Classifier: Programming Language :: Python :: 3.11
Classifier: Programming Language :: Python :: 3.12
Classifier: Programming Language :: Python :: 3.13
Classifier: Topic :: Communications
Classifier: Topic :: Internet :: WWW/HTTP
Classifier: Topic :: Software Development :: Libraries :: Python Modules
Classifier: Typing :: Typed
Requires-Python: >=3.9
Requires-Dist: pydantic>=2.0.0
Requires-Dist: pytest-cov>=7.0.0
Requires-Dist: pytest>=8.4.2
Requires-Dist: requests>=2.25.0
Provides-Extra: dev
Requires-Dist: black>=23.0.0; extra == 'dev'
Requires-Dist: mypy>=1.0.0; extra == 'dev'
Requires-Dist: pytest-cov>=4.0.0; extra == 'dev'
Requires-Dist: pytest>=7.0.0; extra == 'dev'
Requires-Dist: ruff>=0.1.0; extra == 'dev'
